pyoperacionesmonzon/__init__.py
pyoperacionesmonzon-0.2.dist-info/LICENSE
pyoperacionesmonzon-0.2.dist-info/METADATA
pyoperacionesmonzon-0.2.dist-info/WHEEL
pyoperacionesmonzon-0.2.dist-info/top_level.txt
pyoperacionesmonzon-0.2.dist-info/RECORD
