Metadata-Version: 2.1
Name: pyoperacionesmonzon
Version: 0.2
Summary: A tool to perform mathematical operations.
Home-page: UNKNOWN
Author: Jose Manuel Monzón
Author-email: jmmonzonn@gmail.com
License: GNU GPLv3
Keywords: pyoperacionesmonzon math operations
Platform: UNKNOWN
Classifier: Development Status :: 3 - Alpha
Classifier: Topic :: Utilities
Classifier: License :: OSI Approved :: GNU General Public License v3 (GPLv3)
Classifier: Programming Language :: Python :: 3
Classifier: Operating System :: OS Independent
License-File: LICENSE
